kubeagi_cli/__init__.py
kubeagi_cli/cli.py
kubeagi_cli-0.0.1.dist-info/METADATA
kubeagi_cli-0.0.1.dist-info/WHEEL
kubeagi_cli-0.0.1.dist-info/entry_points.txt
kubeagi_cli-0.0.1.dist-info/top_level.txt
kubeagi_cli-0.0.1.dist-info/RECORD
