Metadata-Version: 2.1
Name: kubeagi_cli
Version: 0.0.1
Project-URL: Homepage, https://github.com/kubeagi/core-library
Project-URL: Issues, https://github.com/kubeagi/core-library/issues
Classifier: Programming Language :: Python :: 3
Classifier: License :: OSI Approved :: MIT License
Classifier: Operating System :: OS Independent
Requires-Python: >=3.8
Requires-Dist: typer ==0.9.0
Provides-Extra: dev
Requires-Dist: black ==23.3.0 ; extra == 'dev'
Requires-Dist: pylint ==3.1.0 ; extra == 'dev'
